README.rst
setup.py
pypqueue/__init__.py
pypqueue.egg-info/PKG-INFO
pypqueue.egg-info/SOURCES.txt
pypqueue.egg-info/dependency_links.txt
pypqueue.egg-info/pbr.json
pypqueue.egg-info/top_level.txt