Metadata-Version: 1.1
Name: pypqueue
Version: 2.0.0
Summary: Python interface to submit jobs to http://github.com/ljosa/go-pqueue
Home-page: http://github.com/ljosa/pypqueue
Author: Vebjorn Ljosa
Author-email: vebjorn@ljosa.com
License: BSD
Download-URL: https://github.com/ljosa/pypqueue/tarball/2.0.0
Platform: UNKNOWN
